{"scheme_code":"148611","meta":{"fund_house":"HDFC Mutual Fund","scheme_name":"HDFC Dividend Yield Fund - IDCW Plan","scheme_type":"Open Ended Schemes","scheme_category":"Equity Scheme - Dividend Yield Fund","isin_growth":"INF179KC1AS7","isin_div_reinvestment":"INF179KC1AT5"},"metrics":{"latest_nav":19.547,"latest_date":"23-07-2026","history_points":1377,"min_nav":9.969,"max_nav":24.952,"returns_pct":{"1m":-0.1,"3m":0.89,"6m":-6.68,"1y":-9.44,"3y":20.42,"5y":55.36},"cagr_pct":{"1y":-9.44,"3y":6.39,"5y":9.21}},"nav_history":[{"date":"18-12-2020","nav":10.005},{"date":"21-12-2020","nav":10.003},{"date":"22-12-2020","nav":10.016},{"date":"23-12-2020","nav":10.033},{"date":"24-12-2020","nav":10.046},{"date":"28-12-2020","nav":10.08},{"date":"29-12-2020","nav":10.068},{"date":"30-12-2020","nav":10.074},{"date":"31-12-2020","nav":10.072},{"date":"01-01-2021","nav":10.089},{"date":"04-01-2021","nav":10.19},{"date":"05-01-2021","nav":10.222},{"date":"06-01-2021","nav":10.254},{"date":"07-01-2021","nav":10.289},{"date":"08-01-2021","nav":10.378},{"date":"11-01-2021","nav":10.394},{"date":"12-01-2021","nav":10.46},{"date":"13-01-2021","nav":10.489},{"date":"14-01-2021","nav":10.524},{"date":"15-01-2021","nav":10.454},{"date":"18-01-2021","nav":10.302},{"date":"19-01-2021","nav":10.419},{"date":"20-01-2021","nav":10.495},{"date":"21-01-2021","nav":10.44},{"date":"22-01-2021","nav":10.347},{"date":"25-01-2021","nav":10.236},{"date":"27-01-2021","nav":10.153},{"date":"28-01-2021","nav":10.09},{"date":"29-01-2021","nav":9.969},{"date":"01-02-2021","nav":10.207},{"date":"02-02-2021","nav":10.398},{"date":"03-02-2021","nav":10.506},{"date":"04-02-2021","nav":10.649},{"date":"05-02-2021","nav":10.656},{"date":"08-02-2021","nav":10.805},{"date":"09-02-2021","nav":10.745},{"date":"10-02-2021","nav":10.761},{"date":"11-02-2021","nav":10.809},{"date":"12-02-2021","nav":10.794},{"date":"15-02-2021","nav":10.85},{"date":"16-02-2021","nav":10.848},{"date":"17-02-2021","nav":10.84},{"date":"18-02-2021","nav":10.91},{"date":"19-02-2021","nav":10.819},{"date":"22-02-2021","nav":10.644},{"date":"23-02-2021","nav":10.702},{"date":"24-02-2021","nav":10.793},{"date":"25-02-2021","nav":10.956},{"date":"26-02-2021","nav":10.752},{"date":"01-03-2021","nav":10.938},{"date":"02-03-2021","nav":11.084},{"date":"03-03-2021","nav":11.2},{"date":"04-03-2021","nav":11.235},{"date":"05-03-2021","nav":11.073},{"date":"08-03-2021","nav":11.133},{"date":"09-03-2021","nav":11.135},{"date":"10-03-2021","nav":11.206},{"date":"12-03-2021","nav":11.152},{"date":"15-03-2021","nav":11.137},{"date":"16-03-2021","nav":11.132},{"date":"17-03-2021","nav":10.945},{"date":"18-03-2021","nav":10.807},{"date":"19-03-2021","nav":10.903},{"date":"22-03-2021","nav":10.939},{"date":"23-03-2021","nav":10.946},{"date":"24-03-2021","nav":10.782},{"date":"25-03-2021","nav":10.587},{"date":"26-03-2021","nav":10.71},{"date":"30-03-2021","nav":10.91},{"date":"31-03-2021","nav":10.93},{"date":"01-04-2021","nav":11.016},{"date":"05-04-2021","nav":10.879},{"date":"06-04-2021","nav":10.895},{"date":"07-04-2021","nav":11.001},{"date":"08-04-2021","nav":11.076},{"date":"09-04-2021","nav":11.081},{"date":"12-04-2021","nav":10.658},{"date":"13-04-2021","nav":10.726},{"date":"15-04-2021","nav":10.77},{"date":"16-04-2021","nav":10.844},{"date":"19-04-2021","nav":10.656},{"date":"20-04-2021","nav":10.651},{"date":"22-04-2021","nav":10.678},{"date":"23-04-2021","nav":10.679},{"date":"26-04-2021","nav":10.79},{"date":"27-04-2021","nav":10.877},{"date":"28-04-2021","nav":10.928},{"date":"29-04-2021","nav":10.944},{"date":"30-04-2021","nav":10.875},{"date":"03-05-2021","nav":10.935},{"date":"04-05-2021","nav":10.895},{"date":"05-05-2021","nav":10.994},{"date":"06-05-2021","nav":11.042},{"date":"07-05-2021","nav":11.111},{"date":"10-05-2021","nav":11.267},{"date":"11-05-2021","nav":11.341},{"date":"12-05-2021","nav":11.314},{"date":"14-05-2021","nav":11.248},{"date":"17-05-2021","nav":11.373},{"date":"18-05-2021","nav":11.501},{"date":"19-05-2021","nav":11.513},{"date":"20-05-2021","nav":11.453},{"date":"21-05-2021","nav":11.559},{"date":"24-05-2021","nav":11.579},{"date":"25-05-2021","nav":11.627},{"date":"26-05-2021","nav":11.679},{"date":"27-05-2021","nav":11.708},{"date":"28-05-2021","nav":11.657},{"date":"31-05-2021","nav":11.727},{"date":"01-06-2021","nav":11.706},{"date":"02-06-2021","nav":11.751},{"date":"03-06-2021","nav":11.838},{"date":"04-06-2021","nav":11.866},{"date":"07-06-2021","nav":12.038},{"date":"08-06-2021","nav":12.143},{"date":"09-06-2021","nav":12.089},{"date":"10-06-2021","nav":12.245},{"date":"11-06-2021","nav":12.261},{"date":"14-06-2021","nav":12.24},{"date":"15-06-2021","nav":12.261},{"date":"16-06-2021","nav":12.24},{"date":"17-06-2021","nav":12.194},{"date":"18-06-2021","nav":12.103},{"date":"21-06-2021","nav":12.129},{"date":"22-06-2021","nav":12.182},{"date":"23-06-2021","nav":12.14},{"date":"24-06-2021","nav":12.216},{"date":"25-06-2021","nav":12.267},{"date":"28-06-2021","nav":12.281},{"date":"29-06-2021","nav":12.25},{"date":"30-06-2021","nav":12.266},{"date":"01-07-2021","nav":12.283},{"date":"02-07-2021","nav":12.303},{"date":"05-07-2021","nav":12.378},{"date":"06-07-2021","nav":12.315},{"date":"07-07-2021","nav":12.371},{"date":"08-07-2021","nav":12.313},{"date":"09-07-2021","nav":12.343},{"date":"12-07-2021","nav":12.375},{"date":"13-07-2021","nav":12.453},{"date":"14-07-2021","nav":12.486},{"date":"15-07-2021","nav":12.516},{"date":"16-07-2021","nav":12.547},{"date":"19-07-2021","nav":12.513},{"date":"20-07-2021","nav":12.388},{"date":"22-07-2021","nav":12.555},{"date":"23-07-2021","nav":12.582},{"date":"26-07-2021","nav":12.601},{"date":"27-07-2021","nav":12.595},{"date":"28-07-2021","nav":12.616},{"date":"29-07-2021","nav":12.711},{"date":"30-07-2021","nav":12.788},{"date":"02-08-2021","nav":12.866},{"date":"03-08-2021","nav":12.953},{"date":"04-08-2021","nav":12.917},{"date":"05-08-2021","nav":12.91},{"date":"06-08-2021","nav":12.893},{"date":"09-08-2021","nav":12.893},{"date":"10-08-2021","nav":12.807},{"date":"11-08-2021","nav":12.798},{"date":"12-08-2021","nav":12.956},{"date":"13-08-2021","nav":13.041},{"date":"16-08-2021","nav":13.0},{"date":"17-08-2021","nav":13.074},{"date":"18-08-2021","nav":13.068},{"date":"20-08-2021","nav":12.896},{"date":"23-08-2021","nav":12.869},{"date":"24-08-2021","nav":13.001},{"date":"25-08-2021","nav":13.06},{"date":"26-08-2021","nav":13.05},{"date":"27-08-2021","nav":13.124},{"date":"30-08-2021","nav":13.281},{"date":"31-08-2021","nav":13.434},{"date":"01-09-2021","nav":13.414},{"date":"02-09-2021","nav":13.528},{"date":"03-09-2021","nav":13.596},{"date":"06-09-2021","nav":13.631},{"date":"07-09-2021","nav":13.599},{"date":"08-09-2021","nav":13.63},{"date":"09-09-2021","nav":13.665},{"date":"13-09-2021","nav":13.698},{"date":"14-09-2021","nav":13.801},{"date":"15-09-2021","nav":13.967},{"date":"16-09-2021","nav":13.992},{"date":"17-09-2021","nav":13.902},{"date":"20-09-2021","nav":13.761},{"date":"21-09-2021","nav":13.828},{"date":"22-09-2021","nav":13.912},{"date":"23-09-2021","nav":14.034},{"date":"24-09-2021","nav":14.03},{"date":"27-09-2021","nav":14.002},{"date":"28-09-2021","nav":13.969},{"date":"29-09-2021","nav":14.028},{"date":"30-09-2021","nav":14.062},{"date":"01-10-2021","nav":14.037},{"date":"04-10-2021","nav":14.2},{"date":"05-10-2021","nav":14.326},{"date":"06-10-2021","nav":14.187},{"date":"07-10-2021","nav":14.355},{"date":"08-10-2021","nav":14.449},{"date":"11-10-2021","nav":14.467},{"date":"12-10-2021","nav":14.49},{"date":"13-10-2021","nav":14.616},{"date":"14-10-2021","nav":14.723},{"date":"18-10-2021","nav":14.921},{"date":"19-10-2021","nav":14.713},{"date":"20-10-2021","nav":14.472},{"date":"21-10-2021","nav":14.45},{"date":"22-10-2021","nav":14.321},{"date":"25-10-2021","nav":14.225},{"date":"26-10-2021","nav":14.362},{"date":"27-10-2021","nav":14.384},{"date":"28-10-2021","nav":14.142},{"date":"29-10-2021","nav":14.059},{"date":"01-11-2021","nav":14.269},{"date":"02-11-2021","nav":14.339},{"date":"03-11-2021","nav":14.338},{"date":"08-11-2021","nav":14.62},{"date":"09-11-2021","nav":14.597},{"date":"10-11-2021","nav":14.573},{"date":"11-11-2021","nav":14.492},{"date":"12-11-2021","nav":14.605},{"date":"15-11-2021","nav":14.553},{"date":"16-11-2021","nav":14.538},{"date":"17-11-2021","nav":14.476},{"date":"18-11-2021","nav":14.279},{"date":"22-11-2021","nav":14.015},{"date":"23-11-2021","nav":14.138},{"date":"24-11-2021","nav":14.128},{"date":"25-11-2021","nav":14.17},{"date":"26-11-2021","nav":13.773},{"date":"29-11-2021","nav":13.689},{"date":"30-11-2021","nav":13.915},{"date":"01-12-2021","nav":14.029},{"date":"02-12-2021","nav":14.158},{"date":"03-12-2021","nav":14.097},{"date":"06-12-2021","nav":13.868},{"date":"07-12-2021","nav":14.029},{"date":"08-12-2021","nav":14.221},{"date":"09-12-2021","nav":14.277},{"date":"10-12-2021","nav":14.256},{"date":"13-12-2021","nav":14.208},{"date":"14-12-2021","nav":14.254},{"date":"15-12-2021","nav":14.215},{"date":"16-12-2021","nav":14.171},{"date":"17-12-2021","nav":13.968},{"date":"20-12-2021","nav":13.596},{"date":"21-12-2021","nav":13.781},{"date":"22-12-2021","nav":13.959},{"date":"23-12-2021","nav":14.088},{"date":"24-12-2021","nav":14.002},{"date":"27-12-2021","nav":14.043},{"date":"28-12-2021","nav":14.177},{"date":"29-12-2021","nav":14.186},{"date":"30-12-2021","nav":14.188},{"date":"31-12-2021","nav":14.282},{"date":"03-01-2022","nav":14.475},{"date":"04-01-2022","nav":14.606},{"date":"05-01-2022","nav":14.598},{"date":"06-01-2022","nav":14.527},{"date":"07-01-2022","nav":14.563},{"date":"10-01-2022","nav":14.7},{"date":"11-01-2022","nav":14.672},{"date":"12-01-2022","nav":14.828},{"date":"13-01-2022","nav":14.893},{"date":"14-01-2022","nav":14.904},{"date":"17-01-2022","nav":14.989},{"date":"18-01-2022","nav":14.787},{"date":"19-01-2022","nav":14.768},{"date":"20-01-2022","nav":14.661},{"date":"21-01-2022","nav":14.462},{"date":"24-01-2022","nav":14.051},{"date":"25-01-2022","nav":14.18},{"date":"27-01-2022","nav":14.072},{"date":"28-01-2022","nav":14.111},{"date":"31-01-2022","nav":14.261},{"date":"01-02-2022","nav":14.426},{"date":"02-02-2022","nav":14.562},{"date":"03-02-2022","nav":14.427},{"date":"04-02-2022","nav":14.389},{"date":"07-02-2022","nav":14.236},{"date":"08-02-2022","nav":14.176},{"date":"09-02-2022","nav":14.334},{"date":"10-02-2022","nav":14.416},{"date":"11-02-2022","nav":14.216},{"date":"14-02-2022","nav":13.787},{"date":"15-02-2022","nav":14.117},{"date":"16-02-2022","nav":14.105},{"date":"17-02-2022","nav":14.078},{"date":"18-02-2022","nav":14.035},{"date":"21-02-2022","nav":13.912},{"date":"22-02-2022","nav":13.752},{"date":"23-02-2022","nav":13.765},{"date":"24-02-2022","nav":13.117},{"date":"25-02-2022","nav":13.495},{"date":"28-02-2022","nav":13.649},{"date":"02-03-2022","nav":13.646},{"date":"03-03-2022","nav":13.668},{"date":"04-03-2022","nav":13.501},{"date":"07-03-2022","nav":13.309},{"date":"08-03-2022","nav":13.449},{"date":"09-03-2022","nav":13.623},{"date":"10-03-2022","nav":13.76},{"date":"11-03-2022","nav":12.832},{"date":"14-03-2022","nav":12.923},{"date":"15-03-2022","nav":12.731},{"date":"16-03-2022","nav":12.931},{"date":"17-03-2022","nav":13.038},{"date":"21-03-2022","nav":13.003},{"date":"22-03-2022","nav":13.108},{"date":"23-03-2022","nav":13.087},{"date":"24-03-2022","nav":13.12},{"date":"25-03-2022","nav":13.059},{"date":"28-03-2022","nav":13.129},{"date":"29-03-2022","nav":13.137},{"date":"30-03-2022","nav":13.171},{"date":"31-03-2022","nav":13.184},{"date":"01-04-2022","nav":13.341},{"date":"04-04-2022","nav":13.54},{"date":"05-04-2022","nav":13.609},{"date":"06-04-2022","nav":13.579},{"date":"07-04-2022","nav":13.534},{"date":"08-04-2022","nav":13.637},{"date":"11-04-2022","nav":13.633},{"date":"12-04-2022","nav":13.47},{"date":"13-04-2022","nav":13.522},{"date":"18-04-2022","nav":13.397},{"date":"19-04-2022","nav":13.23},{"date":"20-04-2022","nav":13.333},{"date":"21-04-2022","nav":13.488},{"date":"22-04-2022","nav":13.335},{"date":"25-04-2022","nav":13.097},{"date":"26-04-2022","nav":13.255},{"date":"27-04-2022","nav":13.136},{"date":"28-04-2022","nav":13.291},{"date":"29-04-2022","nav":13.16},{"date":"02-05-2022","nav":13.121},{"date":"04-05-2022","nav":12.869},{"date":"05-05-2022","nav":12.888},{"date":"06-05-2022","nav":12.767},{"date":"09-05-2022","nav":12.654},{"date":"10-05-2022","nav":12.542},{"date":"11-05-2022","nav":12.406},{"date":"12-05-2022","nav":12.221},{"date":"13-05-2022","nav":12.26},{"date":"16-05-2022","nav":12.343},{"date":"17-05-2022","nav":12.655},{"date":"18-05-2022","nav":12.635},{"date":"19-05-2022","nav":12.337},{"date":"20-05-2022","nav":12.605},{"date":"23-05-2022","nav":12.575},{"date":"24-05-2022","nav":12.428},{"date":"25-05-2022","nav":12.262},{"date":"26-05-2022","nav":12.393},{"date":"27-05-2022","nav":12.519},{"date":"30-05-2022","nav":12.735},{"date":"31-05-2022","nav":12.766},{"date":"01-06-2022","nav":12.734},{"date":"02-06-2022","nav":12.775},{"date":"03-06-2022","nav":12.706},{"date":"06-06-2022","nav":12.679},{"date":"07-06-2022","nav":12.587},{"date":"08-06-2022","nav":12.558},{"date":"09-06-2022","nav":12.611},{"date":"10-06-2022","nav":12.482},{"date":"13-06-2022","nav":12.131},{"date":"14-06-2022","nav":12.102},{"date":"15-06-2022","nav":12.099},{"date":"16-06-2022","nav":11.787},{"date":"17-06-2022","nav":11.681},{"date":"20-06-2022","nav":11.636},{"date":"21-06-2022","nav":11.904},{"date":"22-06-2022","nav":11.745},{"date":"23-06-2022","nav":11.863},{"date":"24-06-2022","nav":11.986},{"date":"27-06-2022","nav":12.147},{"date":"28-06-2022","nav":12.205},{"date":"29-06-2022","nav":12.148},{"date":"30-06-2022","nav":12.115},{"date":"01-07-2022","nav":12.167},{"date":"04-07-2022","nav":12.261},{"date":"05-07-2022","nav":12.253},{"date":"06-07-2022","nav":12.372},{"date":"07-07-2022","nav":12.502},{"date":"08-07-2022","nav":12.575},{"date":"11-07-2022","nav":12.581},{"date":"12-07-2022","nav":12.48},{"date":"13-07-2022","nav":12.451},{"date":"14-07-2022","nav":12.442},{"date":"15-07-2022","nav":12.529},{"date":"18-07-2022","nav":12.704},{"date":"19-07-2022","nav":12.773},{"date":"20-07-2022","nav":12.871},{"date":"21-07-2022","nav":12.995},{"date":"22-07-2022","nav":13.01},{"date":"25-07-2022","nav":12.996},{"date":"26-07-2022","nav":12.873},{"date":"27-07-2022","nav":12.985},{"date":"28-07-2022","nav":13.122},{"date":"29-07-2022","nav":13.31},{"date":"01-08-2022","nav":13.423},{"date":"02-08-2022","nav":13.463},{"date":"03-08-2022","nav":13.454},{"date":"04-08-2022","nav":13.452},{"date":"05-08-2022","nav":13.479},{"date":"08-08-2022","nav":13.554},{"date":"10-08-2022","nav":13.58},{"date":"11-08-2022","nav":13.626},{"date":"12-08-2022","nav":13.66},{"date":"16-08-2022","nav":13.752},{"date":"17-08-2022","nav":13.809},{"date":"18-08-2022","nav":13.81},{"date":"19-08-2022","nav":13.687},{"date":"22-08-2022","nav":13.514},{"date":"23-08-2022","nav":13.565},{"date":"24-08-2022","nav":13.604},{"date":"25-08-2022","nav":13.589},{"date":"26-08-2022","nav":13.649},{"date":"29-08-2022","nav":13.491},{"date":"30-08-2022","nav":13.816},{"date":"01-09-2022","nav":13.694},{"date":"02-09-2022","nav":13.719},{"date":"05-09-2022","nav":13.823},{"date":"06-09-2022","nav":13.827},{"date":"07-09-2022","nav":13.868},{"date":"08-09-2022","nav":13.986},{"date":"09-09-2022","nav":14.03},{"date":"12-09-2022","nav":14.134},{"date":"13-09-2022","nav":14.178},{"date":"14-09-2022","nav":14.149},{"date":"15-09-2022","nav":14.106},{"date":"16-09-2022","nav":13.789},{"date":"19-09-2022","nav":13.861},{"date":"20-09-2022","nav":14.015},{"date":"21-09-2022","nav":13.941},{"date":"22-09-2022","nav":13.941},{"date":"23-09-2022","nav":13.742},{"date":"26-09-2022","nav":13.448},{"date":"27-09-2022","nav":13.456},{"date":"28-09-2022","nav":13.403},{"date":"29-09-2022","nav":13.435},{"date":"30-09-2022","nav":13.574},{"date":"03-10-2022","nav":13.433},{"date":"04-10-2022","nav":13.704},{"date":"06-10-2022","nav":13.8},{"date":"07-10-2022","nav":13.773},{"date":"10-10-2022","nav":13.708},{"date":"11-10-2022","nav":13.494},{"date":"12-10-2022","nav":13.601},{"date":"13-10-2022","nav":13.519},{"date":"14-10-2022","nav":13.596},{"date":"17-10-2022","nav":13.68},{"date":"18-10-2022","nav":13.841},{"date":"19-10-2022","nav":13.796},{"date":"20-10-2022","nav":13.851},{"date":"21-10-2022","nav":13.831},{"date":"25-10-2022","nav":13.955},{"date":"27-10-2022","nav":14.03},{"date":"28-10-2022","nav":13.987},{"date":"31-10-2022","nav":14.116},{"date":"01-11-2022","nav":14.221},{"date":"02-11-2022","nav":14.194},{"date":"03-11-2022","nav":14.165},{"date":"04-11-2022","nav":14.199},{"date":"07-11-2022","nav":14.263},{"date":"09-11-2022","nav":14.203},{"date":"10-11-2022","nav":14.082},{"date":"11-11-2022","nav":14.246},{"date":"14-11-2022","nav":14.2},{"date":"15-11-2022","nav":14.249},{"date":"16-11-2022","nav":14.225},{"date":"17-11-2022","nav":14.169},{"date":"18-11-2022","nav":14.144},{"date":"21-11-2022","nav":14.088},{"date":"22-11-2022","nav":14.164},{"date":"23-11-2022","nav":14.194},{"date":"24-11-2022","nav":14.36},{"date":"25-11-2022","nav":14.434},{"date":"28-11-2022","nav":14.471},{"date":"29-11-2022","nav":14.509},{"date":"30-11-2022","nav":14.603},{"date":"01-12-2022","nav":14.667},{"date":"02-12-2022","nav":14.634},{"date":"05-12-2022","nav":14.641},{"date":"06-12-2022","nav":14.608},{"date":"07-12-2022","nav":14.578},{"date":"08-12-2022","nav":14.611},{"date":"09-12-2022","nav":14.508},{"date":"12-12-2022","nav":14.542},{"date":"13-12-2022","nav":14.608},{"date":"14-12-2022","nav":14.681},{"date":"15-12-2022","nav":14.523},{"date":"16-12-2022","nav":14.396},{"date":"19-12-2022","nav":14.462},{"date":"20-12-2022","nav":14.421},{"date":"21-12-2022","nav":14.267},{"date":"22-12-2022","nav":14.137},{"date":"23-12-2022","nav":13.796},{"date":"26-12-2022","nav":14.041},{"date":"27-12-2022","nav":14.141},{"date":"28-12-2022","nav":14.152},{"date":"29-12-2022","nav":14.171},{"date":"30-12-2022","nav":14.162},{"date":"02-01-2023","nav":14.263},{"date":"03-01-2023","nav":14.297},{"date":"04-01-2023","nav":14.155},{"date":"05-01-2023","nav":14.193},{"date":"06-01-2023","nav":14.078},{"date":"09-01-2023","nav":14.245},{"date":"10-01-2023","nav":14.176},{"date":"11-01-2023","nav":14.17},{"date":"12-01-2023","nav":14.173},{"date":"13-01-2023","nav":14.234},{"date":"16-01-2023","nav":14.211},{"date":"17-01-2023","nav":14.29},{"date":"18-01-2023","nav":14.39},{"date":"19-01-2023","nav":14.365},{"date":"20-01-2023","nav":14.29},{"date":"23-01-2023","nav":14.369},{"date":"24-01-2023","nav":14.345},{"date":"25-01-2023","nav":14.184},{"date":"27-01-2023","nav":14.001},{"date":"30-01-2023","nav":13.977},{"date":"31-01-2023","nav":14.085},{"date":"01-02-2023","nav":14.014},{"date":"02-02-2023","nav":14.076},{"date":"03-02-2023","nav":14.186},{"date":"06-02-2023","nav":14.184},{"date":"07-02-2023","nav":14.13},{"date":"08-02-2023","nav":14.201},{"date":"09-02-2023","nav":14.227},{"date":"10-02-2023","nav":14.213},{"date":"13-02-2023","nav":14.157},{"date":"14-02-2023","nav":14.22},{"date":"15-02-2023","nav":14.342},{"date":"16-02-2023","nav":14.419},{"date":"17-02-2023","nav":14.355},{"date":"20-02-2023","nav":14.316},{"date":"21-02-2023","nav":14.294},{"date":"22-02-2023","nav":14.134},{"date":"23-02-2023","nav":14.141},{"date":"24-02-2023","nav":14.096},{"date":"27-02-2023","nav":13.955},{"date":"28-02-2023","nav":13.893},{"date":"01-03-2023","nav":14.039},{"date":"02-03-2023","nav":13.984},{"date":"03-03-2023","nav":14.13},{"date":"06-03-2023","nav":14.243},{"date":"08-03-2023","nav":14.319},{"date":"09-03-2023","nav":14.237},{"date":"10-03-2023","nav":14.16},{"date":"13-03-2023","nav":14.003},{"date":"14-03-2023","nav":13.906},{"date":"15-03-2023","nav":13.888},{"date":"16-03-2023","nav":13.893},{"date":"17-03-2023","nav":13.944},{"date":"20-03-2023","nav":13.83},{"date":"21-03-2023","nav":13.865},{"date":"22-03-2023","nav":13.9},{"date":"23-03-2023","nav":13.877},{"date":"24-03-2023","nav":13.742},{"date":"27-03-2023","nav":13.723},{"date":"28-03-2023","nav":13.675},{"date":"29-03-2023","nav":13.832},{"date":"31-03-2023","nav":14.017},{"date":"03-04-2023","nav":14.078},{"date":"05-04-2023","nav":14.197},{"date":"06-04-2023","nav":14.242},{"date":"10-04-2023","nav":14.299},{"date":"11-04-2023","nav":14.358},{"date":"12-04-2023","nav":14.397},{"date":"13-04-2023","nav":14.365},{"date":"17-04-2023","nav":14.274},{"date":"18-04-2023","nav":14.268},{"date":"19-04-2023","nav":14.204},{"date":"20-04-2023","nav":14.217},{"date":"21-04-2023","nav":14.212},{"date":"24-04-2023","nav":14.269},{"date":"25-04-2023","nav":14.289},{"date":"26-04-2023","nav":14.35},{"date":"27-04-2023","nav":14.402},{"date":"28-04-2023","nav":14.515},{"date":"02-05-2023","nav":14.617},{"date":"03-05-2023","nav":14.618},{"date":"04-05-2023","nav":14.7},{"date":"05-05-2023","nav":14.594},{"date":"08-05-2023","nav":14.702},{"date":"09-05-2023","nav":14.678},{"date":"10-05-2023","nav":14.703},{"date":"11-05-2023","nav":14.709},{"date":"12-05-2023","nav":14.681},{"date":"15-05-2023","nav":14.775},{"date":"16-05-2023","nav":14.753},{"date":"17-05-2023","nav":14.705},{"date":"18-05-2023","nav":14.641},{"date":"19-05-2023","nav":14.678},{"date":"22-05-2023","nav":14.777},{"date":"23-05-2023","nav":14.783},{"date":"24-05-2023","nav":14.789},{"date":"25-05-2023","nav":14.782},{"date":"26-05-2023","nav":14.897},{"date":"29-05-2023","nav":14.948},{"date":"30-05-2023","nav":14.99},{"date":"31-05-2023","nav":14.958},{"date":"01-06-2023","nav":14.957},{"date":"02-06-2023","nav":15.024},{"date":"05-06-2023","nav":15.081},{"date":"06-06-2023","nav":15.111},{"date":"07-06-2023","nav":15.252},{"date":"08-06-2023","nav":15.171},{"date":"09-06-2023","nav":15.14},{"date":"12-06-2023","nav":15.207},{"date":"13-06-2023","nav":15.31},{"date":"14-06-2023","nav":15.321},{"date":"15-06-2023","nav":15.303},{"date":"16-06-2023","nav":15.389},{"date":"19-06-2023","nav":15.359},{"date":"20-06-2023","nav":15.415},{"date":"21-06-2023","nav":15.46},{"date":"22-06-2023","nav":15.369},{"date":"23-06-2023","nav":15.267},{"date":"26-06-2023","nav":15.298},{"date":"27-06-2023","nav":15.368},{"date":"28-06-2023","nav":15.475},{"date":"30-06-2023","nav":15.657},{"date":"03-07-2023","nav":15.706},{"date":"04-07-2023","nav":15.731},{"date":"05-07-2023","nav":15.801},{"date":"06-07-2023","nav":15.916},{"date":"07-07-2023","nav":15.809},{"date":"10-07-2023","nav":15.779},{"date":"11-07-2023","nav":15.91},{"date":"12-07-2023","nav":15.915},{"date":"13-07-2023","nav":15.881},{"date":"14-07-2023","nav":16.044},{"date":"17-07-2023","nav":16.113},{"date":"18-07-2023","nav":16.116},{"date":"19-07-2023","nav":16.222},{"date":"20-07-2023","nav":16.305},{"date":"21-07-2023","nav":16.207},{"date":"24-07-2023","nav":16.232},{"date":"25-07-2023","nav":16.242},{"date":"26-07-2023","nav":16.339},{"date":"27-07-2023","nav":16.334},{"date":"28-07-2023","nav":16.36},{"date":"31-07-2023","nav":16.555},{"date":"01-08-2023","nav":16.598},{"date":"02-08-2023","nav":16.418},{"date":"03-08-2023","nav":16.375},{"date":"04-08-2023","nav":16.476},{"date":"07-08-2023","nav":16.548},{"date":"08-08-2023","nav":16.557},{"date":"09-08-2023","nav":16.638},{"date":"10-08-2023","nav":16.57},{"date":"11-08-2023","nav":16.495},{"date":"14-08-2023","nav":16.466},{"date":"16-08-2023","nav":16.497},{"date":"17-08-2023","nav":16.452},{"date":"18-08-2023","nav":16.418},{"date":"21-08-2023","nav":16.525},{"date":"22-08-2023","nav":16.549},{"date":"23-08-2023","nav":16.63},{"date":"24-08-2023","nav":16.622},{"date":"25-08-2023","nav":16.516},{"date":"28-08-2023","nav":16.585},{"date":"29-08-2023","nav":16.664},{"date":"30-08-2023","nav":16.688},{"date":"31-08-2023","nav":16.626},{"date":"01-09-2023","nav":16.785},{"date":"04-09-2023","nav":16.976},{"date":"05-09-2023","nav":17.042},{"date":"06-09-2023","nav":17.073},{"date":"07-09-2023","nav":17.237},{"date":"08-09-2023","nav":17.393},{"date":"11-09-2023","nav":17.541},{"date":"12-09-2023","nav":17.251},{"date":"13-09-2023","nav":17.329},{"date":"14-09-2023","nav":17.45},{"date":"15-09-2023","nav":17.515},{"date":"18-09-2023","nav":17.467},{"date":"20-09-2023","nav":17.339},{"date":"21-09-2023","nav":17.21},{"date":"22-09-2023","nav":17.199},{"date":"25-09-2023","nav":17.18},{"date":"26-09-2023","nav":17.153},{"date":"27-09-2023","nav":17.259},{"date":"29-09-2023","nav":17.284},{"date":"03-10-2023","nav":17.237},{"date":"04-10-2023","nav":17.099},{"date":"05-10-2023","nav":17.154},{"date":"06-10-2023","nav":17.261},{"date":"09-10-2023","nav":17.114},{"date":"10-10-2023","nav":17.294},{"date":"11-10-2023","nav":17.387},{"date":"12-10-2023","nav":17.4},{"date":"13-10-2023","nav":17.368},{"date":"16-10-2023","nav":17.372},{"date":"17-10-2023","nav":17.454},{"date":"18-10-2023","nav":17.327},{"date":"19-10-2023","nav":17.291},{"date":"20-10-2023","nav":17.163},{"date":"23-10-2023","nav":16.792},{"date":"25-10-2023","nav":16.659},{"date":"26-10-2023","nav":16.446},{"date":"27-10-2023","nav":16.667},{"date":"30-10-2023","nav":16.723},{"date":"31-10-2023","nav":16.698},{"date":"01-11-2023","nav":16.601},{"date":"02-11-2023","nav":16.805},{"date":"03-11-2023","nav":16.91},{"date":"06-11-2023","nav":17.049},{"date":"07-11-2023","nav":17.074},{"date":"08-11-2023","nav":17.158},{"date":"09-11-2023","nav":17.147},{"date":"10-11-2023","nav":17.189},{"date":"13-11-2023","nav":17.296},{"date":"15-11-2023","nav":17.48},{"date":"16-11-2023","nav":17.582},{"date":"17-11-2023","nav":17.592},{"date":"20-11-2023","nav":17.614},{"date":"21-11-2023","nav":17.682},{"date":"22-11-2023","nav":17.706},{"date":"23-11-2023","nav":17.728},{"date":"24-11-2023","nav":17.681},{"date":"28-11-2023","nav":17.759},{"date":"29-11-2023","nav":17.926},{"date":"30-11-2023","nav":18.007},{"date":"01-12-2023","nav":18.212},{"date":"04-12-2023","nav":18.577},{"date":"05-12-2023","nav":18.711},{"date":"06-12-2023","nav":18.779},{"date":"07-12-2023","nav":18.781},{"date":"08-12-2023","nav":18.765},{"date":"11-12-2023","nav":18.814},{"date":"12-12-2023","nav":18.709},{"date":"13-12-2023","nav":18.89},{"date":"14-12-2023","nav":19.091},{"date":"15-12-2023","nav":19.297},{"date":"18-12-2023","nav":19.294},{"date":"19-12-2023","nav":19.331},{"date":"20-12-2023","nav":18.852},{"date":"21-12-2023","nav":19.025},{"date":"22-12-2023","nav":19.16},{"date":"26-12-2023","nav":19.278},{"date":"27-12-2023","nav":19.365},{"date":"28-12-2023","nav":19.529},{"date":"29-12-2023","nav":19.541},{"date":"01-01-2024","nav":19.669},{"date":"02-01-2024","nav":19.599},{"date":"03-01-2024","nav":19.531},{"date":"04-01-2024","nav":19.697},{"date":"05-01-2024","nav":19.768},{"date":"08-01-2024","nav":19.555},{"date":"09-01-2024","nav":19.625},{"date":"10-01-2024","nav":19.598},{"date":"11-01-2024","nav":19.663},{"date":"12-01-2024","nav":19.88},{"date":"15-01-2024","nav":20.06},{"date":"16-01-2024","nav":19.963},{"date":"17-01-2024","nav":19.687},{"date":"18-01-2024","nav":19.659},{"date":"19-01-2024","nav":19.912},{"date":"23-01-2024","nav":19.464},{"date":"24-01-2024","nav":19.803},{"date":"25-01-2024","nav":19.779},{"date":"29-01-2024","nav":20.194},{"date":"30-01-2024","nav":20.082},{"date":"31-01-2024","nav":20.272},{"date":"01-02-2024","nav":20.221},{"date":"02-02-2024","nav":20.403},{"date":"05-02-2024","nav":20.443},{"date":"06-02-2024","nav":20.627},{"date":"07-02-2024","nav":20.618},{"date":"08-02-2024","nav":20.513},{"date":"09-02-2024","nav":20.35},{"date":"12-02-2024","nav":19.931},{"date":"13-02-2024","nav":20.087},{"date":"14-02-2024","nav":20.265},{"date":"15-02-2024","nav":20.422},{"date":"16-02-2024","nav":20.523},{"date":"19-02-2024","nav":20.576},{"date":"20-02-2024","nav":20.565},{"date":"21-02-2024","nav":20.371},{"date":"22-02-2024","nav":20.555},{"date":"23-02-2024","nav":20.581},{"date":"26-02-2024","nav":20.546},{"date":"27-02-2024","nav":20.556},{"date":"28-02-2024","nav":20.282},{"date":"29-02-2024","nav":20.348},{"date":"01-03-2024","nav":20.61},{"date":"04-03-2024","nav":20.766},{"date":"05-03-2024","nav":20.78},{"date":"06-03-2024","nav":20.705},{"date":"07-03-2024","nav":20.774},{"date":"11-03-2024","nav":20.569},{"date":"12-03-2024","nav":20.42},{"date":"13-03-2024","nav":19.808},{"date":"14-03-2024","nav":20.088},{"date":"15-03-2024","nav":19.952},{"date":"18-03-2024","nav":19.938},{"date":"19-03-2024","nav":19.721},{"date":"20-03-2024","nav":19.722},{"date":"21-03-2024","nav":20.048},{"date":"22-03-2024","nav":20.155},{"date":"26-03-2024","nav":20.161},{"date":"27-03-2024","nav":20.226},{"date":"28-03-2024","nav":20.406},{"date":"31-03-2024","nav":20.403},{"date":"01-04-2024","nav":20.645},{"date":"02-04-2024","nav":20.706},{"date":"03-04-2024","nav":20.783},{"date":"04-04-2024","nav":20.911},{"date":"05-04-2024","nav":20.916},{"date":"08-04-2024","nav":21.007},{"date":"09-04-2024","nav":20.96},{"date":"10-04-2024","nav":21.054},{"date":"12-04-2024","nav":20.901},{"date":"15-04-2024","nav":20.738},{"date":"16-04-2024","nav":20.716},{"date":"18-04-2024","nav":20.575},{"date":"19-04-2024","nav":20.618},{"date":"22-04-2024","nav":20.805},{"date":"23-04-2024","nav":20.895},{"date":"24-04-2024","nav":20.969},{"date":"25-04-2024","nav":21.126},{"date":"26-04-2024","nav":21.115},{"date":"29-04-2024","nav":21.245},{"date":"30-04-2024","nav":21.223},{"date":"02-05-2024","nav":21.296},{"date":"03-05-2024","nav":21.182},{"date":"06-05-2024","nav":21.059},{"date":"07-05-2024","nav":20.864},{"date":"08-05-2024","nav":20.941},{"date":"09-05-2024","nav":20.572},{"date":"10-05-2024","nav":20.705},{"date":"13-05-2024","nav":20.705},{"date":"14-05-2024","nav":20.868},{"date":"15-05-2024","nav":20.944},{"date":"16-05-2024","nav":21.121},{"date":"17-05-2024","nav":21.269},{"date":"21-05-2024","nav":21.402},{"date":"22-05-2024","nav":21.484},{"date":"23-05-2024","nav":21.689},{"date":"24-05-2024","nav":21.728},{"date":"27-05-2024","nav":21.719},{"date":"28-05-2024","nav":21.624},{"date":"29-05-2024","nav":21.539},{"date":"30-05-2024","nav":21.323},{"date":"31-05-2024","nav":21.379},{"date":"03-06-2024","nav":22.065},{"date":"04-06-2024","nav":20.464},{"date":"05-06-2024","nav":21.14},{"date":"06-06-2024","nav":21.537},{"date":"07-06-2024","nav":21.944},{"date":"10-06-2024","nav":22.002},{"date":"11-06-2024","nav":22.099},{"date":"12-06-2024","nav":22.228},{"date":"13-06-2024","nav":22.336},{"date":"14-06-2024","nav":22.448},{"date":"18-06-2024","nav":22.552},{"date":"19-06-2024","nav":22.466},{"date":"20-06-2024","nav":22.553},{"date":"21-06-2024","nav":22.554},{"date":"24-06-2024","nav":22.574},{"date":"25-06-2024","nav":22.702},{"date":"26-06-2024","nav":22.781},{"date":"27-06-2024","nav":22.802},{"date":"28-06-2024","nav":22.845},{"date":"01-07-2024","nav":23.099},{"date":"02-07-2024","nav":23.085},{"date":"03-07-2024","nav":23.253},{"date":"04-07-2024","nav":23.318},{"date":"05-07-2024","nav":23.431},{"date":"08-07-2024","nav":23.478},{"date":"09-07-2024","nav":23.579},{"date":"10-07-2024","nav":23.513},{"date":"11-07-2024","nav":23.603},{"date":"12-07-2024","nav":23.702},{"date":"15-07-2024","nav":23.798},{"date":"16-07-2024","nav":23.824},{"date":"18-07-2024","nav":23.814},{"date":"19-07-2024","nav":23.432},{"date":"22-07-2024","nav":23.524},{"date":"23-07-2024","nav":23.421},{"date":"24-07-2024","nav":23.546},{"date":"25-07-2024","nav":23.564},{"date":"26-07-2024","nav":23.935},{"date":"29-07-2024","nav":24.033},{"date":"30-07-2024","nav":24.074},{"date":"31-07-2024","nav":24.143},{"date":"01-08-2024","nav":24.129},{"date":"02-08-2024","nav":23.85},{"date":"05-08-2024","nav":23.136},{"date":"06-08-2024","nav":23.056},{"date":"07-08-2024","nav":23.465},{"date":"08-08-2024","nav":23.313},{"date":"09-08-2024","nav":23.536},{"date":"12-08-2024","nav":23.533},{"date":"13-08-2024","nav":23.336},{"date":"14-08-2024","nav":23.279},{"date":"16-08-2024","nav":23.652},{"date":"19-08-2024","nav":23.744},{"date":"20-08-2024","nav":23.905},{"date":"21-08-2024","nav":24.009},{"date":"22-08-2024","nav":24.016},{"date":"23-08-2024","nav":24.003},{"date":"26-08-2024","nav":24.16},{"date":"27-08-2024","nav":24.248},{"date":"28-08-2024","nav":24.248},{"date":"29-08-2024","nav":24.246},{"date":"30-08-2024","nav":24.351},{"date":"02-09-2024","nav":24.358},{"date":"03-09-2024","nav":24.496},{"date":"04-09-2024","nav":24.442},{"date":"05-09-2024","nav":24.436},{"date":"06-09-2024","nav":24.157},{"date":"09-09-2024","nav":24.104},{"date":"10-09-2024","nav":24.277},{"date":"11-09-2024","nav":24.136},{"date":"12-09-2024","nav":24.529},{"date":"13-09-2024","nav":24.562},{"date":"16-09-2024","nav":24.575},{"date":"17-09-2024","nav":24.6},{"date":"18-09-2024","nav":24.466},{"date":"19-09-2024","nav":24.36},{"date":"20-09-2024","nav":24.619},{"date":"23-09-2024","nav":24.795},{"date":"24-09-2024","nav":24.802},{"date":"25-09-2024","nav":24.806},{"date":"26-09-2024","nav":24.913},{"date":"27-09-2024","nav":24.952},{"date":"30-09-2024","nav":24.741},{"date":"01-10-2024","nav":24.773},{"date":"03-10-2024","nav":24.287},{"date":"04-10-2024","nav":24.091},{"date":"07-10-2024","nav":23.686},{"date":"08-10-2024","nav":23.981},{"date":"09-10-2024","nav":24.076},{"date":"10-10-2024","nav":24.081},{"date":"11-10-2024","nav":24.075},{"date":"14-10-2024","nav":24.209},{"date":"15-10-2024","nav":24.246},{"date":"16-10-2024","nav":24.238},{"date":"17-10-2024","nav":23.934},{"date":"18-10-2024","nav":24.017},{"date":"21-10-2024","nav":23.855},{"date":"22-10-2024","nav":23.387},{"date":"23-10-2024","nav":23.379},{"date":"24-10-2024","nav":23.308},{"date":"25-10-2024","nav":22.968},{"date":"28-10-2024","nav":23.087},{"date":"29-10-2024","nav":23.217},{"date":"30-10-2024","nav":23.239},{"date":"31-10-2024","nav":23.236},{"date":"04-11-2024","nav":23.047},{"date":"05-11-2024","nav":23.251},{"date":"06-11-2024","nav":23.581},{"date":"07-11-2024","nav":23.386},{"date":"08-11-2024","nav":23.248},{"date":"11-11-2024","nav":23.191},{"date":"12-11-2024","nav":22.906},{"date":"13-11-2024","nav":22.475},{"date":"14-11-2024","nav":22.442},{"date":"18-11-2024","nav":22.298},{"date":"19-11-2024","nav":22.42},{"date":"21-11-2024","nav":22.196},{"date":"22-11-2024","nav":22.588},{"date":"25-11-2024","nav":22.898},{"date":"26-11-2024","nav":22.917},{"date":"27-11-2024","nav":23.031},{"date":"28-11-2024","nav":22.851},{"date":"29-11-2024","nav":23.029},{"date":"02-12-2024","nav":23.135},{"date":"03-12-2024","nav":23.357},{"date":"04-12-2024","nav":23.437},{"date":"05-12-2024","nav":23.566},{"date":"06-12-2024","nav":23.63},{"date":"09-12-2024","nav":23.613},{"date":"10-12-2024","nav":23.618},{"date":"11-12-2024","nav":23.662},{"date":"12-12-2024","nav":23.528},{"date":"13-12-2024","nav":23.631},{"date":"16-12-2024","nav":23.64},{"date":"17-12-2024","nav":23.421},{"date":"18-12-2024","nav":23.231},{"date":"19-12-2024","nav":23.065},{"date":"20-12-2024","nav":22.634},{"date":"23-12-2024","nav":22.67},{"date":"24-12-2024","nav":22.699},{"date":"26-12-2024","nav":22.711},{"date":"27-12-2024","nav":22.749},{"date":"30-12-2024","nav":22.621},{"date":"31-12-2024","nav":22.699},{"date":"01-01-2025","nav":22.82},{"date":"02-01-2025","nav":23.151},{"date":"03-01-2025","nav":23.067},{"date":"06-01-2025","nav":22.586},{"date":"07-01-2025","nav":22.698},{"date":"08-01-2025","nav":22.571},{"date":"09-01-2025","nav":22.378},{"date":"10-01-2025","nav":22.126},{"date":"13-01-2025","nav":21.59},{"date":"14-01-2025","nav":21.818},{"date":"15-01-2025","nav":21.878},{"date":"16-01-2025","nav":22.044},{"date":"17-01-2025","nav":22.026},{"date":"20-01-2025","nav":22.149},{"date":"21-01-2025","nav":21.81},{"date":"22-01-2025","nav":21.741},{"date":"23-01-2025","nav":21.793},{"date":"24-01-2025","nav":21.557},{"date":"27-01-2025","nav":21.148},{"date":"28-01-2025","nav":21.068},{"date":"29-01-2025","nav":21.382},{"date":"30-01-2025","nav":21.402},{"date":"31-01-2025","nav":21.735},{"date":"03-02-2025","nav":21.392},{"date":"04-02-2025","nav":21.709},{"date":"05-02-2025","nav":21.837},{"date":"06-02-2025","nav":21.792},{"date":"07-02-2025","nav":21.76},{"date":"10-02-2025","nav":21.495},{"date":"11-02-2025","nav":21.045},{"date":"12-02-2025","nav":20.993},{"date":"13-02-2025","nav":21.016},{"date":"14-02-2025","nav":20.717},{"date":"17-02-2025","nav":20.714},{"date":"18-02-2025","nav":20.675},{"date":"19-02-2025","nav":20.809},{"date":"20-02-2025","nav":20.906},{"date":"21-02-2025","nav":20.797},{"date":"24-02-2025","nav":20.552},{"date":"25-02-2025","nav":20.475},{"date":"27-02-2025","nav":20.344},{"date":"28-02-2025","nav":19.893},{"date":"03-03-2025","nav":18.368},{"date":"04-03-2025","nav":18.405},{"date":"05-03-2025","nav":18.73},{"date":"06-03-2025","nav":18.941},{"date":"07-03-2025","nav":18.945},{"date":"10-03-2025","nav":18.737},{"date":"11-03-2025","nav":18.685},{"date":"12-03-2025","nav":18.639},{"date":"13-03-2025","nav":18.548},{"date":"17-03-2025","nav":18.629},{"date":"18-03-2025","nav":18.962},{"date":"19-03-2025","nav":19.16},{"date":"20-03-2025","nav":19.345},{"date":"21-03-2025","nav":19.565},{"date":"24-03-2025","nav":19.868},{"date":"25-03-2025","nav":19.784},{"date":"26-03-2025","nav":19.601},{"date":"27-03-2025","nav":19.707},{"date":"28-03-2025","nav":19.668},{"date":"31-03-2025","nav":19.666},{"date":"01-04-2025","nav":19.519},{"date":"02-04-2025","nav":19.662},{"date":"03-04-2025","nav":19.656},{"date":"04-04-2025","nav":19.184},{"date":"07-04-2025","nav":18.596},{"date":"08-04-2025","nav":18.932},{"date":"09-04-2025","nav":18.768},{"date":"11-04-2025","nav":19.146},{"date":"15-04-2025","nav":19.579},{"date":"16-04-2025","nav":19.715},{"date":"17-04-2025","nav":19.914},{"date":"21-04-2025","nav":20.227},{"date":"22-04-2025","nav":20.272},{"date":"23-04-2025","nav":20.404},{"date":"24-04-2025","nav":20.377},{"date":"25-04-2025","nav":20.077},{"date":"28-04-2025","nav":20.326},{"date":"29-04-2025","nav":20.321},{"date":"30-04-2025","nav":20.261},{"date":"02-05-2025","nav":20.254},{"date":"05-05-2025","nav":20.374},{"date":"06-05-2025","nav":20.189},{"date":"07-05-2025","nav":20.274},{"date":"08-05-2025","nav":20.084},{"date":"09-05-2025","nav":19.947},{"date":"12-05-2025","nav":20.654},{"date":"13-05-2025","nav":20.553},{"date":"14-05-2025","nav":20.715},{"date":"15-05-2025","nav":20.939},{"date":"16-05-2025","nav":21.049},{"date":"19-05-2025","nav":21.039},{"date":"20-05-2025","nav":20.785},{"date":"21-05-2025","nav":20.908},{"date":"22-05-2025","nav":20.803},{"date":"23-05-2025","nav":20.944},{"date":"26-05-2025","nav":21.055},{"date":"27-05-2025","nav":20.977},{"date":"28-05-2025","nav":20.955},{"date":"29-05-2025","nav":21.029},{"date":"30-05-2025","nav":20.932},{"date":"02-06-2025","nav":20.921},{"date":"03-06-2025","nav":20.812},{"date":"04-06-2025","nav":20.88},{"date":"05-06-2025","nav":20.956},{"date":"06-06-2025","nav":21.116},{"date":"09-06-2025","nav":21.282},{"date":"10-06-2025","nav":21.31},{"date":"11-06-2025","nav":21.361},{"date":"12-06-2025","nav":21.119},{"date":"13-06-2025","nav":21.015},{"date":"16-06-2025","nav":21.224},{"date":"17-06-2025","nav":21.187},{"date":"18-06-2025","nav":21.134},{"date":"19-06-2025","nav":21.01},{"date":"20-06-2025","nav":21.208},{"date":"23-06-2025","nav":21.143},{"date":"24-06-2025","nav":21.234},{"date":"25-06-2025","nav":21.376},{"date":"26-06-2025","nav":21.521},{"date":"27-06-2025","nav":21.607},{"date":"30-06-2025","nav":21.603},{"date":"01-07-2025","nav":21.626},{"date":"02-07-2025","nav":21.609},{"date":"03-07-2025","nav":21.603},{"date":"04-07-2025","nav":21.666},{"date":"07-07-2025","nav":21.628},{"date":"08-07-2025","nav":21.67},{"date":"09-07-2025","nav":21.671},{"date":"10-07-2025","nav":21.608},{"date":"11-07-2025","nav":21.488},{"date":"14-07-2025","nav":21.469},{"date":"15-07-2025","nav":21.591},{"date":"16-07-2025","nav":21.631},{"date":"17-07-2025","nav":21.574},{"date":"18-07-2025","nav":21.465},{"date":"21-07-2025","nav":21.527},{"date":"22-07-2025","nav":21.49},{"date":"23-07-2025","nav":21.584},{"date":"24-07-2025","nav":21.445},{"date":"25-07-2025","nav":21.223},{"date":"28-07-2025","nav":21.045},{"date":"29-07-2025","nav":21.186},{"date":"30-07-2025","nav":21.231},{"date":"31-07-2025","nav":21.143},{"date":"01-08-2025","nav":20.876},{"date":"04-08-2025","nav":21.023},{"date":"05-08-2025","nav":21.016},{"date":"06-08-2025","nav":20.86},{"date":"07-08-2025","nav":20.899},{"date":"08-08-2025","nav":20.673},{"date":"11-08-2025","nav":20.818},{"date":"12-08-2025","nav":20.824},{"date":"13-08-2025","nav":20.916},{"date":"14-08-2025","nav":20.932},{"date":"18-08-2025","nav":21.125},{"date":"19-08-2025","nav":21.228},{"date":"20-08-2025","nav":21.274},{"date":"21-08-2025","nav":21.304},{"date":"22-08-2025","nav":21.196},{"date":"25-08-2025","nav":21.25},{"date":"26-08-2025","nav":21.013},{"date":"28-08-2025","nav":20.827},{"date":"29-08-2025","nav":20.751},{"date":"01-09-2025","nav":20.956},{"date":"02-09-2025","nav":20.994},{"date":"03-09-2025","nav":21.128},{"date":"04-09-2025","nav":21.061},{"date":"05-09-2025","nav":21.079},{"date":"08-09-2025","nav":21.114},{"date":"09-09-2025","nav":21.193},{"date":"10-09-2025","nav":21.317},{"date":"11-09-2025","nav":21.346},{"date":"12-09-2025","nav":21.423},{"date":"15-09-2025","nav":21.429},{"date":"16-09-2025","nav":21.595},{"date":"17-09-2025","nav":21.662},{"date":"18-09-2025","nav":21.722},{"date":"19-09-2025","nav":21.696},{"date":"22-09-2025","nav":21.572},{"date":"23-09-2025","nav":21.548},{"date":"24-09-2025","nav":21.45},{"date":"25-09-2025","nav":21.346},{"date":"26-09-2025","nav":21.044},{"date":"30-09-2025","nav":21.021},{"date":"01-10-2025","nav":21.204},{"date":"03-10-2025","nav":21.31},{"date":"06-10-2025","nav":21.421},{"date":"07-10-2025","nav":21.462},{"date":"08-10-2025","nav":21.38},{"date":"09-10-2025","nav":21.449},{"date":"10-10-2025","nav":21.538},{"date":"13-10-2025","nav":21.473},{"date":"14-10-2025","nav":21.369},{"date":"15-10-2025","nav":21.525},{"date":"16-10-2025","nav":21.677},{"date":"17-10-2025","nav":21.698},{"date":"20-10-2025","nav":21.797},{"date":"23-10-2025","nav":21.878},{"date":"24-10-2025","nav":21.819},{"date":"27-10-2025","nav":21.939},{"date":"28-10-2025","nav":21.913},{"date":"29-10-2025","nav":22.098},{"date":"30-10-2025","nav":22.005},{"date":"31-10-2025","nav":21.899},{"date":"03-11-2025","nav":21.957},{"date":"04-11-2025","nav":21.806},{"date":"06-11-2025","nav":21.611},{"date":"07-11-2025","nav":21.592},{"date":"10-11-2025","nav":21.654},{"date":"11-11-2025","nav":21.715},{"date":"12-11-2025","nav":21.872},{"date":"13-11-2025","nav":21.88},{"date":"14-11-2025","nav":21.846},{"date":"17-11-2025","nav":21.94},{"date":"18-11-2025","nav":21.825},{"date":"19-11-2025","nav":21.859},{"date":"20-11-2025","nav":21.916},{"date":"21-11-2025","nav":21.745},{"date":"24-11-2025","nav":21.658},{"date":"25-11-2025","nav":21.615},{"date":"26-11-2025","nav":21.878},{"date":"27-11-2025","nav":21.815},{"date":"28-11-2025","nav":21.792},{"date":"01-12-2025","nav":21.792},{"date":"02-12-2025","nav":21.74},{"date":"03-12-2025","nav":21.699},{"date":"04-12-2025","nav":21.704},{"date":"05-12-2025","nav":21.722},{"date":"08-12-2025","nav":21.451},{"date":"09-12-2025","nav":21.446},{"date":"10-12-2025","nav":21.394},{"date":"11-12-2025","nav":21.483},{"date":"12-12-2025","nav":21.607},{"date":"15-12-2025","nav":21.614},{"date":"16-12-2025","nav":21.466},{"date":"17-12-2025","nav":21.408},{"date":"18-12-2025","nav":21.363},{"date":"19-12-2025","nav":21.515},{"date":"22-12-2025","nav":21.689},{"date":"23-12-2025","nav":21.706},{"date":"24-12-2025","nav":21.661},{"date":"26-12-2025","nav":21.589},{"date":"29-12-2025","nav":21.498},{"date":"30-12-2025","nav":21.477},{"date":"31-12-2025","nav":21.681},{"date":"01-01-2026","nav":21.731},{"date":"02-01-2026","nav":21.915},{"date":"05-01-2026","nav":21.885},{"date":"06-01-2026","nav":21.883},{"date":"07-01-2026","nav":21.865},{"date":"08-01-2026","nav":21.575},{"date":"09-01-2026","nav":21.375},{"date":"12-01-2026","nav":21.402},{"date":"13-01-2026","nav":21.416},{"date":"14-01-2026","nav":21.393},{"date":"16-01-2026","nav":21.424},{"date":"19-01-2026","nav":21.314},{"date":"20-01-2026","nav":20.945},{"date":"21-01-2026","nav":20.815},{"date":"22-01-2026","nav":20.947},{"date":"23-01-2026","nav":20.701},{"date":"27-01-2026","nav":20.795},{"date":"28-01-2026","nav":21.032},{"date":"29-01-2026","nav":21.049},{"date":"30-01-2026","nav":21.049},{"date":"02-02-2026","nav":20.887},{"date":"03-02-2026","nav":21.358},{"date":"04-02-2026","nav":21.386},{"date":"05-02-2026","nav":21.294},{"date":"06-02-2026","nav":21.288},{"date":"09-02-2026","nav":21.513},{"date":"10-02-2026","nav":21.648},{"date":"11-02-2026","nav":21.664},{"date":"12-02-2026","nav":21.484},{"date":"13-02-2026","nav":21.235},{"date":"16-02-2026","nav":21.363},{"date":"17-02-2026","nav":21.483},{"date":"18-02-2026","nav":21.553},{"date":"19-02-2026","nav":21.262},{"date":"20-02-2026","nav":21.336},{"date":"23-02-2026","nav":21.402},{"date":"24-02-2026","nav":21.195},{"date":"25-02-2026","nav":21.305},{"date":"26-02-2026","nav":21.359},{"date":"27-02-2026","nav":19.619},{"date":"02-03-2026","nav":19.363},{"date":"04-03-2026","nav":19.021},{"date":"05-03-2026","nav":19.226},{"date":"06-03-2026","nav":19.052},{"date":"09-03-2026","nav":18.675},{"date":"10-03-2026","nav":18.925},{"date":"11-03-2026","nav":18.736},{"date":"12-03-2026","nav":18.617},{"date":"13-03-2026","nav":18.182},{"date":"16-03-2026","nav":18.233},{"date":"17-03-2026","nav":18.343},{"date":"18-03-2026","nav":18.572},{"date":"19-03-2026","nav":18.014},{"date":"20-03-2026","nav":18.12},{"date":"23-03-2026","nav":17.604},{"date":"24-03-2026","nav":17.896},{"date":"25-03-2026","nav":18.214},{"date":"27-03-2026","nav":17.887},{"date":"30-03-2026","nav":17.491},{"date":"31-03-2026","nav":17.49},{"date":"01-04-2026","nav":17.824},{"date":"02-04-2026","nav":17.846},{"date":"06-04-2026","nav":18.056},{"date":"07-04-2026","nav":18.156},{"date":"08-04-2026","nav":18.79},{"date":"09-04-2026","nav":18.722},{"date":"10-04-2026","nav":18.945},{"date":"13-04-2026","nav":18.838},{"date":"15-04-2026","nav":19.214},{"date":"16-04-2026","nav":19.264},{"date":"17-04-2026","nav":19.414},{"date":"20-04-2026","nav":19.433},{"date":"21-04-2026","nav":19.566},{"date":"22-04-2026","nav":19.529},{"date":"23-04-2026","nav":19.374},{"date":"24-04-2026","nav":19.125},{"date":"27-04-2026","nav":19.359},{"date":"28-04-2026","nav":19.3},{"date":"29-04-2026","nav":19.415},{"date":"30-04-2026","nav":19.302},{"date":"04-05-2026","nav":19.439},{"date":"05-05-2026","nav":19.381},{"date":"06-05-2026","nav":19.618},{"date":"07-05-2026","nav":19.7},{"date":"08-05-2026","nav":19.63},{"date":"11-05-2026","nav":19.404},{"date":"12-05-2026","nav":19.027},{"date":"13-05-2026","nav":19.087},{"date":"14-05-2026","nav":19.21},{"date":"15-05-2026","nav":19.162},{"date":"18-05-2026","nav":19.075},{"date":"19-05-2026","nav":19.119},{"date":"20-05-2026","nav":19.132},{"date":"21-05-2026","nav":19.181},{"date":"22-05-2026","nav":19.228},{"date":"25-05-2026","nav":19.463},{"date":"26-05-2026","nav":19.463},{"date":"27-05-2026","nav":19.532},{"date":"29-05-2026","nav":19.281},{"date":"01-06-2026","nav":19.145},{"date":"02-06-2026","nav":19.194},{"date":"03-06-2026","nav":19.151},{"date":"04-06-2026","nav":19.211},{"date":"05-06-2026","nav":19.176},{"date":"08-06-2026","nav":18.955},{"date":"09-06-2026","nav":19.107},{"date":"10-06-2026","nav":19.011},{"date":"11-06-2026","nav":18.905},{"date":"12-06-2026","nav":19.239},{"date":"15-06-2026","nav":19.421},{"date":"16-06-2026","nav":19.514},{"date":"17-06-2026","nav":19.575},{"date":"18-06-2026","nav":19.67},{"date":"19-06-2026","nav":19.627},{"date":"22-06-2026","nav":19.736},{"date":"23-06-2026","nav":19.566},{"date":"24-06-2026","nav":19.628},{"date":"25-06-2026","nav":19.627},{"date":"29-06-2026","nav":19.508},{"date":"30-06-2026","nav":19.506},{"date":"01-07-2026","nav":19.541},{"date":"02-07-2026","nav":19.685},{"date":"03-07-2026","nav":19.756},{"date":"06-07-2026","nav":19.855},{"date":"07-07-2026","nav":19.836},{"date":"08-07-2026","nav":19.454},{"date":"09-07-2026","nav":19.596},{"date":"10-07-2026","nav":19.787},{"date":"13-07-2026","nav":19.798},{"date":"14-07-2026","nav":19.667},{"date":"15-07-2026","nav":19.725},{"date":"16-07-2026","nav":19.719},{"date":"17-07-2026","nav":19.817},{"date":"20-07-2026","nav":19.757},{"date":"21-07-2026","nav":19.79},{"date":"22-07-2026","nav":19.654},{"date":"23-07-2026","nav":19.547}]}